fast_crypt/__init__.py
fast_crypt/auth.py
fast_crypt/cli.py
fast_crypt/decrypt.py
fast_crypt/encrypt.py
fast_crypt/encrypt_name.py
fast_crypt/file_path.py
fast_crypt/get_repo.py
fast_crypt-0.2.2.dist-info/METADATA
fast_crypt-0.2.2.dist-info/WHEEL
fast_crypt-0.2.2.dist-info/entry_points.txt
fast_crypt-0.2.2.dist-info/top_level.txt
fast_crypt-0.2.2.dist-info/RECORD
