Metadata-Version: 2.1
Name: fast-crypt
Version: 0.2.2
Summary: A CLI tool for encrypting and decrypting files using GitHub authentication, with support for Google Cloud Secret Manager.
Home-page: https://github.com/ColeBaxendale/Fast-Crypt
Author: Cole Baxendale
Author-email: thecodercole@gmail.com
Classifier: Programming Language :: Python :: 3
Classifier: Operating System :: OS Independent
Requires-Python: >=3.6
Requires-Dist: click >=7.0
Requires-Dist: cryptography >=3.4.7
Requires-Dist: google-cloud-secret-manager >=2.7.0
Requires-Dist: requests >=2.25.1
Requires-Dist: prompt-toolkit >=3.0.18
